Workbook

Sheet Journal Général
A1: Comptabilité Syndic de Copropriété - Journal Général
A2: Période : Août 2026 | Conformité PCGM & Loi 18-00
A4: Date | B4: Code Journal | C4: N° Compte | D4: Intitulé du compte | E4: Libellé de l'opération | F4: Débit (DH) | G4: Crédit (DH)
A5: 2026-08-01 | B5: VT | C5: 34150001 | D5: Copropriétaire - Appt 01 | E5: Appel de fonds mois Août 2026 | F5: 300
A6: 2026-08-01 | B6: VT | C6: 34150002 | D6: Copropriétaire - Appt 02 | E6: Appel de fonds mois Août 2026 | F6: 300
A7: 2026-08-01 | B7: VT | C7: 34150003 | D7: Copropriétaire - Appt 03 | E7: Appel de fonds mois Août 2026 | F7: 300
A8: 2026-08-01 | B8: VT | C8: 34150004 | D8: Copropriétaire - Appt 04 | E8: Appel de fonds mois Août 2026 | F8: 300
A9: 2026-08-01 | B9: VT | C9: 34150005 | D9: Copropriétaire - Appt 05 | E9: Appel de fonds mois Août 2026 | F9: 300
A10: 2026-08-01 | B10: VT | C10: 34150006 | D10: Copropriétaire - Appt 06 | E10: Appel de fonds mois Août 2026 | F10: 300
A11: 2026-08-01 | B11: VT | C11: 34150007 | D11: Copropriétaire - Appt 07 | E11: Appel de fonds mois Août 2026 | F11: 300
A12: 2026-08-01 | B12: VT | C12: 34150008 | D12: Copropriétaire - Appt 08 | E12: Appel de fonds mois Août 2026 | F12: 300
A13: 2026-08-01 | B13: VT | C13: 34150009 | D13: Copropriétaire - Appt 09 | E13: Appel de fonds mois Août 2026 | F13: 300
A14: 2026-08-01 | B14: VT | C14: 34150010 | D14: Copropriétaire - Appt 10 | E14: Appel de fonds mois Août 2026 | F14: 300
A15: 2026-08-01 | B15: VT | C15: 71810000 | D15: Cotisations des copropriétaires | E15: Appel de fonds global (10 appts) | G15: 3000
A16: 2026-08-05 | B16: BQ | C16: 51410000 | D16: Banque Attijari | E16: Virement reçu Appt 01 (Mois Août) | F16: 300
A17: 2026-08-05 | B17: BQ | C17: 34150001 | D17: Copropriétaire - Appt 01 | E17: Règlement appel de fonds Août | G17: 300
A18: 2026-08-06 | B18: CA | C18: 51610000 | D18: Caisse espèces Syndic | E18: Espèces reçues Appt 03 (Mois Août) | F18: 300
A19: 2026-08-06 | B19: CA | C19: 34150003 | D19: Copropriétaire - Appt 03 | E19: Règlement espèces mois Août | G19: 300
A20: 2026-08-07 | B20: CA | C20: 51610000 | D20: Caisse espèces Syndic | E20: Espèces reçues Appt 04 (4 mois d'avance) | F20: 1200
A21: 2026-08-07 | B21: CA | C21: 34150004 | D21: Copropriétaire - Appt 04 | E21: Imputation solde appel Août | G21: 300
A22: 2026-08-07 | B22: CA | C22: 44150004 | D22: Copropriétaire - Appt 04 | E22: Avance espèces (Sept, Oct, Nov) | G22: 900
A23: 2026-08-10 | B23: BQ | C23: 51410000 | D23: Banque Attijari | E23: Virement reçu Appt 02 (Acompte 1000 DH) | F23: 1000
A24: 2026-08-10 | B24: BQ | C24: 34150002 | D24: Copropriétaire - Appt 02 | E24: Imputation solde appel Août | G24: 300
A25: 2026-08-10 | B25: BQ | C25: 44150002 | D25: Copropriétaire - Appt 02 | E25: Avance / Crédit pour mois futurs | G25: 700
A26: 2026-08-12 | B26: AC | C26: 61220000 | D26: Achats de fournitures d'entretien | E26: Ampoules & produits nettoyage | F26: 150
A27: 2026-08-12 | B27: AC | C27: 44110000 | D27: Fournisseur Bricolage | E27: Facture N° 1045 | G27: 150
A28: 2026-08-13 | B28: CA | C28: 44110000 | D28: Fournisseur Bricolage | E28: Règlement espèces Facture N° 1045 | F28: 150
A29: 2026-08-13 | B29: CA | C29: 51610000 | D29: Caisse espèces Syndic | E29: Paiement fournitures en espèces | G29: 150
A30: 2026-08-28 | B30: OD | C30: 61710000 | D30: Rémunération du personnel | E30: Salaire net gardien mois Août | F30: 2500
A31: 2026-08-28 | B31: OD | C31: 44320000 | D31: Personnel - Rémunérations dues | E31: Salaire gardien à payer | G31: 2500
A32: 2026-08-29 | B32: BQ | C32: 44320000 | D32: Personnel - Rémunérations dues | E32: Virement salaire gardien | F32: 2500
A33: 2026-08-29 | B33: BQ | C33: 51410000 | D33: Banque Attijari | E33: Sortie de trésorerie (Salaire) | G33: 2500
A34: 2026-08-31 | B34: BQ | C34: 61470000 | D34: Services bancaires | E34: Agios & Tenue de compte bancaire | F34: 60
A35: 2026-08-31 | B35: BQ | C35: 51410000 | D35: Banque Attijari | E35: Prélèvement agios bancaires | G35: 60
A36: TOTAL GENERAL | F36: =SUM(F5:F35) | G36: =SUM(G5:G35)
E38: Contrôle d'Équilibre : | F38: =IF(F36=G36, " ÉQUILIBRÉ", " DESÉQUILIBRÉ")

Sheet Grand Livre Copropriétaires
A1: Grand Livre Auxiliaire - Suivi des Copropriétaires
A2: État des soldes au 31/08/2026
A4: N° Compte | B4: Copropriétaire | C4: Appel de fonds (Débit) | D4: Règlements (Crédit) | E4: Solde Net (DH) | F4: Statut Comptable
A5: 34150001 | B5: Appartement 01 | C5: =SUMIF('Journal Général'!$C$5:$C$35, A5, 'Journal Général'!$F$5:$F$35) | D5: =SUMIF('Journal Général'!$C$5:$C$35, A5, 'Journal Général'!$G$5:$G$35) + SUMIF('Journal Général'!$C$5:$C$35, "4415000"&RIGHT(A5,1), 'Journal Général'!$G$5:$G$35) | E5: =C5-D5 | F5: =IF(E5=0, " À jour", IF(E5<0, " En avance (Créditeur)", " En retard (Impayé)"))
A6: 34150002 | B6: Appartement 02 | C6: =SUMIF('Journal Général'!$C$5:$C$35, A6, 'Journal Général'!$F$5:$F$35) | D6: =SUMIF('Journal Général'!$C$5:$C$35, A6, 'Journal Général'!$G$5:$G$35) + SUMIF('Journal Général'!$C$5:$C$35, "4415000"&RIGHT(A6,1), 'Journal Général'!$G$5:$G$35) | E6: =C6-D6 | F6: =IF(E6=0, " À jour", IF(E6<0, " En avance (Créditeur)", " En retard (Impayé)"))
A7: 34150003 | B7: Appartement 03 | C7: =SUMIF('Journal Général'!$C$5:$C$35, A7, 'Journal Général'!$F$5:$F$35) | D7: =SUMIF('Journal Général'!$C$5:$C$35, A7, 'Journal Général'!$G$5:$G$35) + SUMIF('Journal Général'!$C$5:$C$35, "4415000"&RIGHT(A7,1), 'Journal Général'!$G$5:$G$35) | E7: =C7-D7 | F7: =IF(E7=0, " À jour", IF(E7<0, " En avance (Créditeur)", " En retard (Impayé)"))
A8: 34150004 | B8: Appartement 04 | C8: =SUMIF('Journal Général'!$C$5:$C$35, A8, 'Journal Général'!$F$5:$F$35) | D8: =SUMIF('Journal Général'!$C$5:$C$35, A8, 'Journal Général'!$G$5:$G$35) + SUMIF('Journal Général'!$C$5:$C$35, "4415000"&RIGHT(A8,1), 'Journal Général'!$G$5:$G$35) | E8: =C8-D8 | F8: =IF(E8=0, " À jour", IF(E8<0, " En avance (Créditeur)", " En retard (Impayé)"))
A9: 34150005 | B9: Appartement 05 | C9: =SUMIF('Journal Général'!$C$5:$C$35, A9, 'Journal Général'!$F$5:$F$35) | D9: =SUMIF('Journal Général'!$C$5:$C$35, A9, 'Journal Général'!$G$5:$G$35) + SUMIF('Journal Général'!$C$5:$C$35, "4415000"&RIGHT(A9,1), 'Journal Général'!$G$5:$G$35) | E9: =C9-D9 | F9: =IF(E9=0, " À jour", IF(E9<0, " En avance (Créditeur)", " En retard (Impayé)"))
A10: 34150006 | B10: Appartement 06 | C10: =SUMIF('Journal Général'!$C$5:$C$35, A10, 'Journal Général'!$F$5:$F$35) | D10: =SUMIF('Journal Général'!$C$5:$C$35, A10, 'Journal Général'!$G$5:$G$35) + SUMIF('Journal Général'!$C$5:$C$35, "4415000"&RIGHT(A10,1), 'Journal Général'!$G$5:$G$35) | E10: =C10-D10 | F10: =IF(E10=0, " À jour", IF(E10<0, " En avance (Créditeur)", " En retard (Impayé)"))
A11: 34150007 | B11: Appartement 07 | C11: =SUMIF('Journal Général'!$C$5:$C$35, A11, 'Journal Général'!$F$5:$F$35) | D11: =SUMIF('Journal Général'!$C$5:$C$35, A11, 'Journal Général'!$G$5:$G$35) + SUMIF('Journal Général'!$C$5:$C$35, "4415000"&RIGHT(A11,1), 'Journal Général'!$G$5:$G$35) | E11: =C11-D11 | F11: =IF(E11=0, " À jour", IF(E11<0, " En avance (Créditeur)", " En retard (Impayé)"))
A12: 34150008 | B12: Appartement 08 | C12: =SUMIF('Journal Général'!$C$5:$C$35, A12, 'Journal Général'!$F$5:$F$35) | D12: =SUMIF('Journal Général'!$C$5:$C$35, A12, 'Journal Général'!$G$5:$G$35) + SUMIF('Journal Général'!$C$5:$C$35, "4415000"&RIGHT(A12,1), 'Journal Général'!$G$5:$G$35) | E12: =C12-D12 | F12: =IF(E12=0, " À jour", IF(E12<0, " En avance (Créditeur)", " En retard (Impayé)"))
A13: 34150009 | B13: Appartement 09 | C13: =SUMIF('Journal Général'!$C$5:$C$35, A13, 'Journal Général'!$F$5:$F$35) | D13: =SUMIF('Journal Général'!$C$5:$C$35, A13, 'Journal Général'!$G$5:$G$35) + SUMIF('Journal Général'!$C$5:$C$35, "4415000"&RIGHT(A13,1), 'Journal Général'!$G$5:$G$35) | E13: =C13-D13 | F13: =IF(E13=0, " À jour", IF(E13<0, " En avance (Créditeur)", " En retard (Impayé)"))
A14: 34150010 | B14: Appartement 10 | C14: =SUMIF('Journal Général'!$C$5:$C$35, A14, 'Journal Général'!$F$5:$F$35) | D14: =SUMIF('Journal Général'!$C$5:$C$35, A14, 'Journal Général'!$G$5:$G$35) + SUMIF('Journal Général'!$C$5:$C$35, "4415000"&RIGHT(A14,1), 'Journal Général'!$G$5:$G$35) | E14: =C14-D14 | F14: =IF(E14=0, " À jour", IF(E14<0, " En avance (Créditeur)", " En retard (Impayé)"))
A15: TOTAL | C15: =SUM(C5:C14) | D15: =SUM(D5:D14) | E15: =SUM(E5:E14)

Sheet CPC & Trésorerie
A1: Compte de Produits et Charges (CPC) & Synthèse Trésorerie
A2: Période : Août 2026
A4: COMPTE DE PRODUITS ET CHARGES (CPC) | E4: SYNTHÈSE DE TRÉSORERIE (BANQUE & CAISSE)
A5: Poste | B5: Intitulé des comptes | C5: Montant (DH) | E5: Compte | F5: Libellé | G5: Entrées (Débit) | H5: Sorties (Crédit) | I5: Solde Disponible
A6: PRODUITS | B6: 71810000 - Cotisations des copropriétaires | C6: =SUMIF('Journal Général'!$C$5:$C$35, "71810000", 'Journal Général'!$G$5:$G$35) | E6: 51410000 | F6: Banque Attijariwafa Bank | G6: =SUMIF('Journal Général'!$C$5:$C$35, "51410000", 'Journal Général'!$F$5:$F$35) | H6: =SUMIF('Journal Général'!$C$5:$C$35, "51410000", 'Journal Général'!$G$5:$G$35) | I6: =G6-H6
A7: CHARGES | B7: 61220000 - Achats de fournitures d'entretien | C7: =SUMIF('Journal Général'!$C$5:$C$35, "61220000", 'Journal Général'!$F$5:$F$35) | E7: 51610000 | F7: Caisse Espèces Syndic | G7: =SUMIF('Journal Général'!$C$5:$C$35, "51610000", 'Journal Général'!$F$5:$F$35) | H7: =SUMIF('Journal Général'!$C$5:$C$35, "51610000", 'Journal Général'!$G$5:$G$35) | I7: =G7-H7
A8: CHARGES | B8: 61710000 - Rémunération du personnel (Gardien) | C8: =SUMIF('Journal Général'!$C$5:$C$35, "61710000", 'Journal Général'!$F$5:$F$35) | E8: TOTAL | G8: =SUM(G6:G7) | H8: =SUM(H6:H7) | I8: =SUM(I6:I7)
A9: CHARGES | B9: 61470000 - Services bancaires & agios | C9: =SUMIF('Journal Général'!$C$5:$C$35, "61470000", 'Journal Général'!$F$5:$F$35)
A10: TOTAL PRODUITS | C10: =C6
A11: TOTAL CHARGES | C11: =SUM(C7:C9)
A12: RÉSULTAT (EXCÉDENT) | C12: =C10-C11
